ashyq/__init__.py
ashyq/ashyq.py
ashyq/exceptions.py
ashyq/types.py
ashyq/utils.py
ashyq/drivers/__init__.py
ashyq/drivers/a_sync.py
ashyq/drivers/base.py
ashyq/drivers/sync.py
ashyq-0.1.0.post2.dist-info/LICENSE
ashyq-0.1.0.post2.dist-info/METADATA
ashyq-0.1.0.post2.dist-info/WHEEL
ashyq-0.1.0.post2.dist-info/top_level.txt
ashyq-0.1.0.post2.dist-info/RECORD
